WuaiPojieLuntanjinghuaJi2018DiwuBufenFix1/README.md
WuaiPojieLuntanjinghuaJi2018DiwuBufenFix1/__init__.py
WuaiPojieLuntanjinghuaJi2018DiwuBufenFix1/__main__.py
WuaiPojieLuntanjinghuaJi2018DiwuBufenFix1/file.epub
WuaiPojieLuntanjinghuaJi2018DiwuBufenFix1/index.html
WuaiPojieLuntanjinghuaJi2018DiwuBufenFix1/css/__init__.py
WuaiPojieLuntanjinghuaJi2018DiwuBufenFix1/css/annotations.css
WuaiPojieLuntanjinghuaJi2018DiwuBufenFix1/css/main.css
WuaiPojieLuntanjinghuaJi2018DiwuBufenFix1/css/normalize.css
WuaiPojieLuntanjinghuaJi2018DiwuBufenFix1/css/popup.css
WuaiPojieLuntanjinghuaJi2018DiwuBufenFix1/font/__init__.py
WuaiPojieLuntanjinghuaJi2018DiwuBufenFix1/font/fontello.eot
WuaiPojieLuntanjinghuaJi2018DiwuBufenFix1/font/fontello.svg
WuaiPojieLuntanjinghuaJi2018DiwuBufenFix1/font/fontello.ttf
WuaiPojieLuntanjinghuaJi2018DiwuBufenFix1/font/fontello.woff
WuaiPojieLuntanjinghuaJi2018DiwuBufenFix1/img/__init__.py
WuaiPojieLuntanjinghuaJi2018DiwuBufenFix1/img/annotator-glyph-sprite.png
WuaiPojieLuntanjinghuaJi2018DiwuBufenFix1/img/annotator-icon-sprite.png
WuaiPojieLuntanjinghuaJi2018DiwuBufenFix1/img/apple-touch-icon.png
WuaiPojieLuntanjinghuaJi2018DiwuBufenFix1/img/cancelfullscreen.png
WuaiPojieLuntanjinghuaJi2018DiwuBufenFix1/img/close.png
WuaiPojieLuntanjinghuaJi2018DiwuBufenFix1/img/fullscreen.png
WuaiPojieLuntanjinghuaJi2018DiwuBufenFix1/img/loader.gif
WuaiPojieLuntanjinghuaJi2018DiwuBufenFix1/img/menu-icon.png
WuaiPojieLuntanjinghuaJi2018DiwuBufenFix1/img/save.png
WuaiPojieLuntanjinghuaJi2018DiwuBufenFix1/img/saved.png
WuaiPojieLuntanjinghuaJi2018DiwuBufenFix1/img/settings-s.png
WuaiPojieLuntanjinghuaJi2018DiwuBufenFix1/img/settings.png
WuaiPojieLuntanjinghuaJi2018DiwuBufenFix1/img/star.png
WuaiPojieLuntanjinghuaJi2018DiwuBufenFix1/js/__init__.py
WuaiPojieLuntanjinghuaJi2018DiwuBufenFix1/js/epub.js
WuaiPojieLuntanjinghuaJi2018DiwuBufenFix1/js/epub.min.js
WuaiPojieLuntanjinghuaJi2018DiwuBufenFix1/js/epub.min.map
WuaiPojieLuntanjinghuaJi2018DiwuBufenFix1/js/hooks.min.js
wuai_pojie_luntanjinghua_ji_2018_diwu_bufen_fix1-2025.3.23.1.dist-info/METADATA
wuai_pojie_luntanjinghua_ji_2018_diwu_bufen_fix1-2025.3.23.1.dist-info/WHEEL
wuai_pojie_luntanjinghua_ji_2018_diwu_bufen_fix1-2025.3.23.1.dist-info/entry_points.txt
wuai_pojie_luntanjinghua_ji_2018_diwu_bufen_fix1-2025.3.23.1.dist-info/top_level.txt
wuai_pojie_luntanjinghua_ji_2018_diwu_bufen_fix1-2025.3.23.1.dist-info/RECORD
